emq/__init__.py
emq/client/__init__.py
emq/client/clientfactory.py
emq/client/constants.py
emq/client/requestchecker.py
emq/client/thttpclient.py
emq/common/EMQBaseService.py
emq/common/__init__.py
emq/common/constants.py
emq/common/ttypes.py
emq/message/MessageService.py
emq/message/__init__.py
emq/message/constants.py
emq/message/ttypes.py
emq/queue/QueueService.py
emq/queue/__init__.py
emq/queue/constants.py
emq/queue/ttypes.py
emq/range/__init__.py
emq/range/constants.py
emq/range/ttypes.py
emq/statistics/StatisticsService.py
emq/statistics/__init__.py
emq/statistics/constants.py
emq/statistics/ttypes.py
emr/__init__.py
emr/client/__init__.py
emr/client/clientfactory.py
emr/client/constants.py
emr/client/emrthttpclient.py
emr/exceptions/GalaxyEmrServiceException.py
emr/exceptions/__init__.py
emr/service/EMRMasterService.py
emr/service/EMRSchedulerService.py
emr/service/__init__.py
emr/service/constants.py
emr/service/ttypes.py
galaxy_sdk_python3-0.6.dist-info/DESCRIPTION.rst
galaxy_sdk_python3-0.6.dist-info/METADATA
galaxy_sdk_python3-0.6.dist-info/RECORD
galaxy_sdk_python3-0.6.dist-info/WHEEL
galaxy_sdk_python3-0.6.dist-info/metadata.json
galaxy_sdk_python3-0.6.dist-info/top_level.txt
rpc/__init__.py
rpc/auth/AuthService.py
rpc/auth/__init__.py
rpc/auth/constants.py
rpc/auth/ttypes.py
rpc/authorization/__init__.py
rpc/authorization/constants.py
rpc/authorization/ttypes.py
rpc/common/BaseService.py
rpc/common/__init__.py
rpc/common/constants.py
rpc/common/ttypes.py
rpc/errors/__init__.py
rpc/errors/constants.py
rpc/errors/ttypes.py
sds/__init__.py
sds/admin/AdminService.py
sds/admin/__init__.py
sds/admin/constants.py
sds/admin/ttypes.py
sds/auth/AuthService.py
sds/auth/__init__.py
sds/auth/constants.py
sds/auth/ttypes.py
sds/client/__init__.py
sds/client/clientfactory.py
sds/client/datumutil.py
sds/client/exceptions.py
sds/client/sdsthttpclient.py
sds/client/tablescanner.py
sds/common/BaseService.py
sds/common/__init__.py
sds/common/constants.py
sds/common/ttypes.py
sds/errors/__init__.py
sds/errors/constants.py
sds/errors/ttypes.py
sds/io/__init__.py
sds/io/constants.py
sds/io/ttypes.py
sds/metrics/Common.py
sds/metrics/__init__.py
