Metadata-Version: 2.0
Name: galaxy-sdk-python3
Version: 0.6
Summary: Xiaomi Galaxy SDK for Python3
Home-page: http://xiangyang.li/project/galaxy-sdk-python
Author: http://xiangyang.li
Author-email: wo@xiangyang.li
License: Apache License (2.0)
Platform: UNKNOWN
Classifier: Development Status :: 4 - Beta
Classifier: Topic :: Software Development :: Libraries
Classifier: License :: OSI Approved :: Apache Software License
Classifier: Intended Audience :: Developers
Requires-Python: >=3
